Siamese_for_face_recognization/__init__.py
Siamese_for_face_recognization/models/nn4.small2.v1.h5
Siamese_for_face_recognization-0.0.2.dist-info/AUTHORS.rst
Siamese_for_face_recognization-0.0.2.dist-info/LICENSE
Siamese_for_face_recognization-0.0.2.dist-info/METADATA
Siamese_for_face_recognization-0.0.2.dist-info/WHEEL
Siamese_for_face_recognization-0.0.2.dist-info/top_level.txt
Siamese_for_face_recognization-0.0.2.dist-info/RECORD
